menuscript.py
menuscript-1.0.6.dist-info/METADATA
menuscript-1.0.6.dist-info/WHEEL
menuscript-1.0.6.dist-info/entry_points.txt
menuscript-1.0.6.dist-info/top_level.txt
menuscript-1.0.6.dist-info/RECORD
