Metadata-Version: 2.1
Name: menuscript
Version: 1.0.6
Summary: A menu-based script generator
Home-page: https://github.com/AIMadeScripts/createmenus
Author: Mr. Robot
Author-email: alertsontwitter@gmail.com
Classifier: Programming Language :: Python :: 3
Classifier: License :: OSI Approved :: MIT License
Classifier: Operating System :: OS Independent
